testsetup/__init__.py
testsetup/hello.py
testsetup/config/t.json
testsetup/utilts/__init__.py
testsetup/utilts/print_info.py
myprinter2-1.6.dist-info/LICENSE
myprinter2-1.6.dist-info/METADATA
myprinter2-1.6.dist-info/WHEEL
myprinter2-1.6.dist-info/top_level.txt
myprinter2-1.6.dist-info/RECORD
