Metadata-Version: 2.1
Name: myprinter2
Version: 1.6
Summary: Test setuptools
Home-page: http://pypi.python.org/pypi/myprinter2/
Author: fshenx
Author-email: 333@qq.com
License: LICENSE
Platform: UNKNOWN
